db_bridge/__init__.py
db_bridge/base_utils.py
db_bridge/config.py
db_bridge/db_utils.py
db_bridge/mysql_utils.py
db_bridge/postgres_utils.py
db_bridge/sqlite_utils.py
db_bridge-0.3.8.dist-info/licenses/LICENSE
db_bridge-0.3.8.dist-info/METADATA
db_bridge-0.3.8.dist-info/WHEEL
db_bridge-0.3.8.dist-info/top_level.txt
db_bridge-0.3.8.dist-info/RECORD
