Metadata-Version: 2.4
Name: db-bridge
Version: 0.3.8
Summary: Minimal Python SQL connector with support for MySQL, SQLite, and PostgreSQL.
Author-email: "Kanad Rishiraj (RoamingSaint)" <roamingsaint27@gmail.com>
License-Expression: MIT
Requires-Python: >=3.7
License-File: LICENSE
Requires-Dist: pymysql>=1.0
Requires-Dist: psycopg2-binary>=2.9
Requires-Dist: AskUser>=0.1
Provides-Extra: color
Requires-Dist: colorfulPyPrint>=0.1; extra == "color"
Dynamic: license-file
